README.md
setup.cfg
setup.py
ayarami/__init__.py
ayarami/base.py
ayarami.egg-info/PKG-INFO
ayarami.egg-info/SOURCES.txt
ayarami.egg-info/dependency_links.txt
ayarami.egg-info/top_level.txt