Metadata-Version: 1.1
Name: ayarami
Version: 0.0.2
Summary: Simple settings object implementation, just like the one in Django.
Home-page: https://gitlab.com/cediddi/ayarami
Author: Umut Karcı
Author-email: cediddi@gmail.com
License: MIT
Platform: UNKNOWN
Classifier: Programming Language :: Python :: 3
Classifier: License :: OSI Approved :: MIT License
Classifier: Operating System :: OS Independent
